<annotation>
	<folder></folder>
	<filename>17061_jpg.rf.7e827a999554a10fca9c0a3ae405c886.jpg</filename>
	<path>17061_jpg.rf.7e827a999554a10fca9c0a3ae405c886.jpg</path>
	<source>
		<database>roboflow.ai</database>
	</source>
	<size>
		<width>472</width>
		<height>303</height>
		<depth>3</depth>
	</size>
	<segmented>0</segmented>
	<object>
		<name>License-plate</name>
		<pose>Unspecified</pose>
		<truncated>0</truncated>
		<difficult>0</difficult>
		<occluded>0</occluded>
		<bndbox>
			<xmin>230</xmin>
			<xmax>329</xmax>
			<ymin>175</ymin>
			<ymax>230</ymax>
		</bndbox>
	</object>
</annotation>
